{"error":"OK","limit":1,"offset":0,"number_of_page_results":1,"number_of_total_results":1,"status_code":1,"results":{"aliases":null,"api_detail_url":"https:\/\/comicvine.gamespot.com\/api\/volume\/4050-32864\/","characters":[{"api_detail_url":"https:\/\/comicvine.gamespot.com\/api\/character\/4005-52130\/","id":52130,"name":"Tom Judge","site_detail_url":"https:\/\/comicvine.gamespot.com\/tom-judge\/4005-52130\/","count":"35"},{"api_detail_url":"https:\/\/comicvine.gamespot.com\/api\/character\/4005-52133\/","id":52133,"name":"Tilly Grimes","site_detail_url":"https:\/\/comicvine.gamespot.com\/tilly-grimes\/4005-52133\/","count":"25"},{"api_detail_url":"https:\/\/comicvine.gamespot.com\/api\/character\/4005-24347\/","id":24347,"name":"Jackie Estacado","site_detail_url":"https:\/\/comicvine.gamespot.com\/jackie-estacado\/4005-24347\/","count":"24"},{"api_detail_url":"https:\/\/comicvine.gamespot.com\/api\/character\/4005-43945\/","id":43945,"name":"The Angelus","site_detail_url":"https:\/\/comicvine.gamespot.com\/the-angelus\/4005-43945\/","count":"23"},{"api_detail_url":"https:\/\/comicvine.gamespot.com\/api\/character\/4005-48981\/","id":48981,"name":"Danielle Baptiste","site_detail_url":"https:\/\/comicvine.gamespot.com\/danielle-baptiste\/4005-48981\/","count":"22"},{"api_detail_url":"https:\/\/comicvine.gamespot.com\/api\/character\/4005-18318\/","id":18318,"name":"Sara Pezzini","site_detail_url":"https:\/\/comicvine.gamespot.com\/sara-pezzini\/4005-18318\/","count":"20"},{"api_detail_url":"https:\/\/comicvine.gamespot.com\/api\/character\/4005-43829\/","id":43829,"name":"Magdalena","site_detail_url":"https:\/\/comicvine.gamespot.com\/magdalena\/4005-43829\/","count":"19"},{"api_detail_url":"https:\/\/comicvine.gamespot.com\/api\/character\/4005-18319\/","id":18319,"name":"Witchblade","site_detail_url":"https:\/\/comicvine.gamespot.com\/witchblade\/4005-18319\/","count":"18"},{"api_detail_url":"https:\/\/comicvine.gamespot.com\/api\/character\/4005-48639\/","id":48639,"name":"Hope Pezzini","site_detail_url":"https:\/\/comicvine.gamespot.com\/hope-pezzini\/4005-48639\/","count":"16"},{"api_detail_url":"https:\/\/comicvine.gamespot.com\/api\/character\/4005-56215\/","id":56215,"name":"Aphrodite IV","site_detail_url":"https:\/\/comicvine.gamespot.com\/aphrodite-iv\/4005-56215\/","count":"16"},{"api_detail_url":"https:\/\/comicvine.gamespot.com\/api\/character\/4005-57559\/","id":57559,"name":"Glorianna Silver","site_detail_url":"https:\/\/comicvine.gamespot.com\/glorianna-silver\/4005-57559\/","count":"15"},{"api_detail_url":"https:\/\/comicvine.gamespot.com\/api\/character\/4005-56290\/","id":56290,"name":"Michael Finnegan","site_detail_url":"https:\/\/comicvine.gamespot.com\/michael-finnegan\/4005-56290\/","count":"14"},{"api_detail_url":"https:\/\/comicvine.gamespot.com\/api\/character\/4005-18323\/","id":18323,"name":"Ian Nottingham","site_detail_url":"https:\/\/comicvine.gamespot.com\/ian-nottingham\/4005-18323\/","count":"13"},{"api_detail_url":"https:\/\/comicvine.gamespot.com\/api\/character\/4005-60875\/","id":60875,"name":"Sabine","site_detail_url":"https:\/\/comicvine.gamespot.com\/sabine\/4005-60875\/","count":"12"},{"api_detail_url":"https:\/\/comicvine.gamespot.com\/api\/character\/4005-69653\/","id":69653,"name":"Alina Enstrom","site_detail_url":"https:\/\/comicvine.gamespot.com\/alina-enstrom\/4005-69653\/","count":"12"},{"api_detail_url":"https:\/\/comicvine.gamespot.com\/api\/character\/4005-76893\/","id":76893,"name":"Ji Xi","site_detail_url":"https:\/\/comicvine.gamespot.com\/ji-xi\/4005-76893\/","count":"11"},{"api_detail_url":"https:\/\/comicvine.gamespot.com\/api\/character\/4005-73479\/","id":73479,"name":"Mali","site_detail_url":"https:\/\/comicvine.gamespot.com\/mali\/4005-73479\/","count":"10"},{"api_detail_url":"https:\/\/comicvine.gamespot.com\/api\/character\/4005-15348\/","id":15348,"name":"Curator","site_detail_url":"https:\/\/comicvine.gamespot.com\/curator\/4005-15348\/","count":"9"},{"api_detail_url":"https:\/\/comicvine.gamespot.com\/api\/character\/4005-46761\/","id":46761,"name":"Necromancer","site_detail_url":"https:\/\/comicvine.gamespot.com\/necromancer\/4005-46761\/","count":"9"},{"api_detail_url":"https:\/\/comicvine.gamespot.com\/api\/character\/4005-57289\/","id":57289,"name":"Finch","site_detail_url":"https:\/\/comicvine.gamespot.com\/finch\/4005-57289\/","count":"8"},{"api_detail_url":"https:\/\/comicvine.gamespot.com\/api\/character\/4005-47571\/","id":47571,"name":"Jenny Romano","site_detail_url":"https:\/\/comicvine.gamespot.com\/jenny-romano\/4005-47571\/","count":"7"},{"api_detail_url":"https:\/\/comicvine.gamespot.com\/api\/character\/4005-82604\/","id":82604,"name":"Doctor Rachel Harrision","site_detail_url":"https:\/\/comicvine.gamespot.com\/doctor-rachel-harrision\/4005-82604\/","count":"6"},{"api_detail_url":"https:\/\/comicvine.gamespot.com\/api\/character\/4005-9151\/","id":9151,"name":"Velocity","site_detail_url":"https:\/\/comicvine.gamespot.com\/velocity\/4005-9151\/","count":"5"},{"api_detail_url":"https:\/\/comicvine.gamespot.com\/api\/character\/4005-24467\/","id":24467,"name":"Cyblade","site_detail_url":"https:\/\/comicvine.gamespot.com\/cyblade\/4005-24467\/","count":"5"},{"api_detail_url":"https:\/\/comicvine.gamespot.com\/api\/character\/4005-26501\/","id":26501,"name":"Ripclaw","site_detail_url":"https:\/\/comicvine.gamespot.com\/ripclaw\/4005-26501\/","count":"5"},{"api_detail_url":"https:\/\/comicvine.gamespot.com\/api\/character\/4005-40980\/","id":40980,"name":"Ellis","site_detail_url":"https:\/\/comicvine.gamespot.com\/ellis\/4005-40980\/","count":"5"},{"api_detail_url":"https:\/\/comicvine.gamespot.com\/api\/character\/4005-41824\/","id":41824,"name":"Ballistic","site_detail_url":"https:\/\/comicvine.gamespot.com\/ballistic\/4005-41824\/","count":"5"},{"api_detail_url":"https:\/\/comicvine.gamespot.com\/api\/character\/4005-43914\/","id":43914,"name":"Detective Gleason","site_detail_url":"https:\/\/comicvine.gamespot.com\/detective-gleason\/4005-43914\/","count":"4"},{"api_detail_url":"https:\/\/comicvine.gamespot.com\/api\/character\/4005-18327\/","id":18327,"name":"Julie Pezzini","site_detail_url":"https:\/\/comicvine.gamespot.com\/julie-pezzini\/4005-18327\/","count":"3"},{"api_detail_url":"https:\/\/comicvine.gamespot.com\/api\/character\/4005-40979\/","id":40979,"name":"Wolf","site_detail_url":"https:\/\/comicvine.gamespot.com\/wolf\/4005-40979\/","count":"3"},{"api_detail_url":"https:\/\/comicvine.gamespot.com\/api\/character\/4005-41080\/","id":41080,"name":"Samantha Argent","site_detail_url":"https:\/\/comicvine.gamespot.com\/samantha-argent\/4005-41080\/","count":"3"},{"api_detail_url":"https:\/\/comicvine.gamespot.com\/api\/character\/4005-41088\/","id":41088,"name":"Cloaker","site_detail_url":"https:\/\/comicvine.gamespot.com\/cloaker\/4005-41088\/","count":"2"},{"api_detail_url":"https:\/\/comicvine.gamespot.com\/api\/character\/4005-44424\/","id":44424,"name":"Heatwave","site_detail_url":"https:\/\/comicvine.gamespot.com\/heatwave\/4005-44424\/","count":"2"},{"api_detail_url":"https:\/\/comicvine.gamespot.com\/api\/character\/4005-58589\/","id":58589,"name":"Conductor","site_detail_url":"https:\/\/comicvine.gamespot.com\/conductor\/4005-58589\/","count":"2"},{"api_detail_url":"https:\/\/comicvine.gamespot.com\/api\/character\/4005-77679\/","id":77679,"name":"Interface","site_detail_url":"https:\/\/comicvine.gamespot.com\/interface\/4005-77679\/","count":"2"},{"api_detail_url":"https:\/\/comicvine.gamespot.com\/api\/character\/4005-85149\/","id":85149,"name":"Mike Long","site_detail_url":"https:\/\/comicvine.gamespot.com\/mike-long\/4005-85149\/","count":"2"},{"api_detail_url":"https:\/\/comicvine.gamespot.com\/api\/character\/4005-21923\/","id":21923,"name":"Stryker","site_detail_url":"https:\/\/comicvine.gamespot.com\/stryker\/4005-21923\/","count":"1"},{"api_detail_url":"https:\/\/comicvine.gamespot.com\/api\/character\/4005-43915\/","id":43915,"name":"Kenneth Irons","site_detail_url":"https:\/\/comicvine.gamespot.com\/kenneth-irons\/4005-43915\/","count":"1"},{"api_detail_url":"https:\/\/comicvine.gamespot.com\/api\/character\/4005-49791\/","id":49791,"name":"Azazel","site_detail_url":"https:\/\/comicvine.gamespot.com\/azazel\/4005-49791\/","count":"1"},{"api_detail_url":"https:\/\/comicvine.gamespot.com\/api\/character\/4005-52093\/","id":52093,"name":"Dr. Inder Chandrakhar","site_detail_url":"https:\/\/comicvine.gamespot.com\/dr-inder-chandrakhar\/4005-52093\/","count":"1"},{"api_detail_url":"https:\/\/comicvine.gamespot.com\/api\/character\/4005-61525\/","id":61525,"name":"Wulfgar","site_detail_url":"https:\/\/comicvine.gamespot.com\/wulfgar\/4005-61525\/","count":"1"},{"api_detail_url":"https:\/\/comicvine.gamespot.com\/api\/character\/4005-62333\/","id":62333,"name":"The Foreigner","site_detail_url":"https:\/\/comicvine.gamespot.com\/the-foreigner\/4005-62333\/","count":"1"},{"api_detail_url":"https:\/\/comicvine.gamespot.com\/api\/character\/4005-73816\/","id":73816,"name":"Locke","site_detail_url":"https:\/\/comicvine.gamespot.com\/locke\/4005-73816\/","count":"1"},{"api_detail_url":"https:\/\/comicvine.gamespot.com\/api\/character\/4005-85621\/","id":85621,"name":"Valko Balakov","site_detail_url":"https:\/\/comicvine.gamespot.com\/valko-balakov\/4005-85621\/","count":"1"},{"api_detail_url":"https:\/\/comicvine.gamespot.com\/api\/character\/4005-96079\/","id":96079,"name":"Matthew Strow","site_detail_url":"https:\/\/comicvine.gamespot.com\/matthew-strow\/4005-96079\/","count":"1"},{"api_detail_url":"https:\/\/comicvine.gamespot.com\/api\/character\/4005-103250\/","id":103250,"name":"Josephine Valmont","site_detail_url":"https:\/\/comicvine.gamespot.com\/josephine-valmont\/4005-103250\/","count":"1"},{"api_detail_url":"https:\/\/comicvine.gamespot.com\/api\/character\/4005-109292\/","id":109292,"name":"Salifah Zayid","site_detail_url":"https:\/\/comicvine.gamespot.com\/salifah-zayid\/4005-109292\/","count":"1"},{"api_detail_url":"https:\/\/comicvine.gamespot.com\/api\/character\/4005-117132\/","id":117132,"name":"Benedetta Maria Ferro","site_detail_url":"https:\/\/comicvine.gamespot.com\/benedetta-maria-ferro\/4005-117132\/","count":"1"}],"concepts":[{"api_detail_url":"https:\/\/comicvine.gamespot.com\/api\/concept\/4015-56028\/","id":56028,"name":"Modern Age of  Comics","site_detail_url":"https:\/\/comicvine.gamespot.com\/modern-age-of-comics\/4015-56028\/","count":"41"},{"api_detail_url":"https:\/\/comicvine.gamespot.com\/api\/concept\/4015-55685\/","id":55685,"name":"The 13 Artifacts","site_detail_url":"https:\/\/comicvine.gamespot.com\/the-13-artifacts\/4015-55685\/","count":"25"},{"api_detail_url":"https:\/\/comicvine.gamespot.com\/api\/concept\/4015-57350\/","id":57350,"name":"Wraparound Cover","site_detail_url":"https:\/\/comicvine.gamespot.com\/wraparound-cover\/4015-57350\/","count":"13"},{"api_detail_url":"https:\/\/comicvine.gamespot.com\/api\/concept\/4015-57349\/","id":57349,"name":"Variant Cover","site_detail_url":"https:\/\/comicvine.gamespot.com\/variant-cover\/4015-57349\/","count":"8"},{"api_detail_url":"https:\/\/comicvine.gamespot.com\/api\/concept\/4015-45822\/","id":45822,"name":"The Darkness","site_detail_url":"https:\/\/comicvine.gamespot.com\/the-darkness\/4015-45822\/","count":"4"},{"api_detail_url":"https:\/\/comicvine.gamespot.com\/api\/concept\/4015-56667\/","id":56667,"name":"San Diego Comic-Con Exclusive Variant Cover","site_detail_url":"https:\/\/comicvine.gamespot.com\/san-diego-comic-con-exclusive-variant-cover\/4015-56667\/","count":"2"},{"api_detail_url":"https:\/\/comicvine.gamespot.com\/api\/concept\/4015-56779\/","id":56779,"name":"New York Comic Con Exclusive Variant Cover","site_detail_url":"https:\/\/comicvine.gamespot.com\/new-york-comic-con-exclusive-variant-cover\/4015-56779\/","count":"2"},{"api_detail_url":"https:\/\/comicvine.gamespot.com\/api\/concept\/4015-43734\/","id":43734,"name":"Homage Covers","site_detail_url":"https:\/\/comicvine.gamespot.com\/homage-covers\/4015-43734\/","count":"1"},{"api_detail_url":"https:\/\/comicvine.gamespot.com\/api\/concept\/4015-43738\/","id":43738,"name":"Free Comic Book Day","site_detail_url":"https:\/\/comicvine.gamespot.com\/free-comic-book-day\/4015-43738\/","count":"1"},{"api_detail_url":"https:\/\/comicvine.gamespot.com\/api\/concept\/4015-55694\/","id":55694,"name":"End of the World","site_detail_url":"https:\/\/comicvine.gamespot.com\/end-of-the-world\/4015-55694\/","count":"1"},{"api_detail_url":"https:\/\/comicvine.gamespot.com\/api\/concept\/4015-55759\/","id":55759,"name":"Magic","site_detail_url":"https:\/\/comicvine.gamespot.com\/magic\/4015-55759\/","count":"1"},{"api_detail_url":"https:\/\/comicvine.gamespot.com\/api\/concept\/4015-55909\/","id":55909,"name":"San Diego Comic-Con 2010","site_detail_url":"https:\/\/comicvine.gamespot.com\/san-diego-comic-con-2010\/4015-55909\/","count":"1"},{"api_detail_url":"https:\/\/comicvine.gamespot.com\/api\/concept\/4015-55942\/","id":55942,"name":"New York Comic Con 2010","site_detail_url":"https:\/\/comicvine.gamespot.com\/new-york-comic-con-2010\/4015-55942\/","count":"1"},{"api_detail_url":"https:\/\/comicvine.gamespot.com\/api\/concept\/4015-55953\/","id":55953,"name":"Magick","site_detail_url":"https:\/\/comicvine.gamespot.com\/magick\/4015-55953\/","count":"1"},{"api_detail_url":"https:\/\/comicvine.gamespot.com\/api\/concept\/4015-55995\/","id":55995,"name":"C2E2 2011","site_detail_url":"https:\/\/comicvine.gamespot.com\/c2e2-2011\/4015-55995\/","count":"1"},{"api_detail_url":"https:\/\/comicvine.gamespot.com\/api\/concept\/4015-56033\/","id":56033,"name":"San Diego Comic-Con 2011","site_detail_url":"https:\/\/comicvine.gamespot.com\/san-diego-comic-con-2011\/4015-56033\/","count":"1"},{"api_detail_url":"https:\/\/comicvine.gamespot.com\/api\/concept\/4015-56145\/","id":56145,"name":"New York Comic Con 2012","site_detail_url":"https:\/\/comicvine.gamespot.com\/new-york-comic-con-2012\/4015-56145\/","count":"1"},{"api_detail_url":"https:\/\/comicvine.gamespot.com\/api\/concept\/4015-56670\/","id":56670,"name":"Midtown Comics Exclusive Variant Cover","site_detail_url":"https:\/\/comicvine.gamespot.com\/midtown-comics-exclusive-variant-cover\/4015-56670\/","count":"1"},{"api_detail_url":"https:\/\/comicvine.gamespot.com\/api\/concept\/4015-56672\/","id":56672,"name":"Hastings Exclusive Variant Cover","site_detail_url":"https:\/\/comicvine.gamespot.com\/hastings-exclusive-variant-cover\/4015-56672\/","count":"1"},{"api_detail_url":"https:\/\/comicvine.gamespot.com\/api\/concept\/4015-56899\/","id":56899,"name":"ComicsPRO Exclusive Variant Cover","site_detail_url":"https:\/\/comicvine.gamespot.com\/comicspro-exclusive-variant-cover\/4015-56899\/","count":"1"},{"api_detail_url":"https:\/\/comicvine.gamespot.com\/api\/concept\/4015-56908\/","id":56908,"name":"London Super Con Exclusive Variant Cover","site_detail_url":"https:\/\/comicvine.gamespot.com\/london-super-con-exclusive-variant-cover\/4015-56908\/","count":"1"},{"api_detail_url":"https:\/\/comicvine.gamespot.com\/api\/concept\/4015-56927\/","id":56927,"name":"Collector's Paradise Exclusive Variant Cover","site_detail_url":"https:\/\/comicvine.gamespot.com\/collectors-paradise-exclusive-variant-cover\/4015-56927\/","count":"1"},{"api_detail_url":"https:\/\/comicvine.gamespot.com\/api\/concept\/4015-56929\/","id":56929,"name":"C2E2 Exclusive Variant Cover","site_detail_url":"https:\/\/comicvine.gamespot.com\/c2e2-exclusive-variant-cover\/4015-56929\/","count":"1"},{"api_detail_url":"https:\/\/comicvine.gamespot.com\/api\/concept\/4015-57081\/","id":57081,"name":"VA Comicon Exclusive Variant Cover","site_detail_url":"https:\/\/comicvine.gamespot.com\/va-comicon-exclusive-variant-cover\/4015-57081\/","count":"1"},{"api_detail_url":"https:\/\/comicvine.gamespot.com\/api\/concept\/4015-57344\/","id":57344,"name":"#0 Issues","site_detail_url":"https:\/\/comicvine.gamespot.com\/0-issues\/4015-57344\/","count":"1"}],"count_of_issues":41,"date_added":"2010-05-01 11:38:13","date_last_updated":"2014-11-06 08:49:32","deck":"Vol 1","description":"<p>Originally, Artifacts was set to be a 13 part crossover event involving all the popular Top Cow characters in a universe changing event. After the arc's conclusion, the series continued as an ongoing title, mostly serving as an anthology series for the Top Cow characters that lacked their own books. <a href=\"\/ron-marz\/4040-41799\/\" data-ref-id=\"4040-41799\">Ron Marz<\/a> wrote the majority of the series but, toward the end of the series' run, issues were penned by past winners of Top Cow's annual talent contest. Artifacts concluded after 40 issues.<\/p><h4>Collected Editions<\/h4><ul><li><a href=\"\/artifacts-vol-1\/4000-302639\/\" data-ref-id=\"4000-302639\">Artifacts vol. 1<\/a> (#1-4 and Free Comic Book Day #0)<\/li><li><a href=\"\/artifacts-vol-2\/4000-327557\/\" data-ref-id=\"4000-327557\">Artifacts vol. 2<\/a> (#5-8)<\/li><li><a href=\"\/artifacts-vol-3\/4000-350604\/\" data-ref-id=\"4000-350604\">Artifacts vol. 3<\/a> (#9-13)<\/li><li><a href=\"\/artifacts-vol-4\/4000-350605\/\" data-ref-id=\"4000-350605\">Artifacts vol. 4<\/a> (#14-18)<\/li><li><a href=\"https:\/\/www.comicvine.com\/artifacts-5-vol-5\/4000-404724\/\" data-ref-id=\"4000-404724\">Artifacts vol. 5<\/a> (#19-24)<\/li><li><a href=\"https:\/\/www.comicvine.com\/artifacts-6-volume-6\/4000-441439\/\" data-ref-id=\"4000-441439\">Artifacts vol. 6<\/a> (#25-29)<\/li><\/ul><p>A TPB collecting the <a href=\"\/progeny\/4045-57048\/\" data-ref-id=\"4045-57048\">Progeny <\/a>crossover was also released, featuring Artifacts #25-26, <a href=\"\/witchblade\/4050-7300\/\" data-ref-id=\"4050-7300\">Witchblade<\/a> #164-165, and <a href=\"\/the-darkness\/4050-20086\/\" data-ref-id=\"4050-20086\">The Darkness<\/a> #111:<\/p><ul><li><a href=\"\/\/www.comicvine.com\/progeny-1-vol-1\/4000-423958\/\" data-ref-id=\"4000-423958\"> Progeny vol. 1<\/a><\/li><\/ul>","first_issue":{"api_detail_url":"https:\/\/comicvine.gamespot.com\/api\/issue\/4000-211451\/","id":211451,"name":null,"issue_number":null},"id":32864,"image":{"icon_url":"https:\/\/comicvine.gamespot.com\/api\/image\/square_avatar\/2322564-01a.jpg","medium_url":"https:\/\/comicvine.gamespot.com\/api\/image\/scale_medium\/2322564-01a.jpg","screen_url":"https:\/\/comicvine.gamespot.com\/api\/image\/screen_medium\/2322564-01a.jpg","screen_large_url":"https:\/\/comicvine.gamespot.com\/api\/image\/screen_kubrick\/2322564-01a.jpg","small_url":"https:\/\/comicvine.gamespot.com\/api\/image\/scale_small\/2322564-01a.jpg","super_url":"https:\/\/comicvine.gamespot.com\/api\/image\/scale_large\/2322564-01a.jpg","thumb_url":"https:\/\/comicvine.gamespot.com\/api\/image\/scale_avatar\/2322564-01a.jpg","tiny_url":"https:\/\/comicvine.gamespot.com\/api\/image\/square_mini\/2322564-01a.jpg","original_url":"https:\/\/comicvine.gamespot.com\/api\/image\/original\/2322564-01a.jpg","image_tags":"All Images"},"issues":[{"api_detail_url":"https:\/\/comicvine.gamespot.com\/api\/issue\/4000-211451\/","id":211451,"name":"","site_detail_url":"https:\/\/comicvine.gamespot.com\/artifacts-0\/4000-211451\/","issue_number":"0"},{"api_detail_url":"https:\/\/comicvine.gamespot.com\/api\/issue\/4000-226876\/","id":226876,"name":"\"Artifacts\" part 1 of 13; \"Origin: Witchblade\"","site_detail_url":"https:\/\/comicvine.gamespot.com\/artifacts-1-artifacts-part-1-of-13-origin-witchbla\/4000-226876\/","issue_number":"1"},{"api_detail_url":"https:\/\/comicvine.gamespot.com\/api\/issue\/4000-236452\/","id":236452,"name":"\"Artifacts\" part 2 of 13; \"Origin: The Darkness\"","site_detail_url":"https:\/\/comicvine.gamespot.com\/artifacts-2-artifacts-part-2-of-13-origin-the-dark\/4000-236452\/","issue_number":"2"},{"api_detail_url":"https:\/\/comicvine.gamespot.com\/api\/issue\/4000-239876\/","id":239876,"name":"\"Artifacts\" part 3 of 13; \"Origin: Angelus\"","site_detail_url":"https:\/\/comicvine.gamespot.com\/artifacts-3-artifacts-part-3-of-13-origin-angelus\/4000-239876\/","issue_number":"3"},{"api_detail_url":"https:\/\/comicvine.gamespot.com\/api\/issue\/4000-250788\/","id":250788,"name":"\"Artifacts\" part 4 of 13; \"Origin: Blood Sword\"","site_detail_url":"https:\/\/comicvine.gamespot.com\/artifacts-4-artifacts-part-4-of-13-origin-blood-sw\/4000-250788\/","issue_number":"4"},{"api_detail_url":"https:\/\/comicvine.gamespot.com\/api\/issue\/4000-259490\/","id":259490,"name":"\"Artifacts\" part 5 of 13; \"Origin: Ember Stone\"","site_detail_url":"https:\/\/comicvine.gamespot.com\/artifacts-5-artifacts-part-5-of-13-origin-ember-st\/4000-259490\/","issue_number":"5"},{"api_detail_url":"https:\/\/comicvine.gamespot.com\/api\/issue\/4000-266052\/","id":266052,"name":"\"Artifacts\" part 6 of 13; Origin: \"Coin of Solomon\"","site_detail_url":"https:\/\/comicvine.gamespot.com\/artifacts-6-artifacts-part-6-of-13-origin-coin-of-\/4000-266052\/","issue_number":"6"},{"api_detail_url":"https:\/\/comicvine.gamespot.com\/api\/issue\/4000-269525\/","id":269525,"name":"\"Artifacts\" part 7 of 13; \"Origin: Coin of Solomon\"","site_detail_url":"https:\/\/comicvine.gamespot.com\/artifacts-7-artifacts-part-7-of-13-origin-coin-of-\/4000-269525\/","issue_number":"7"},{"api_detail_url":"https:\/\/comicvine.gamespot.com\/api\/issue\/4000-276826\/","id":276826,"name":"\"Artifacts\" part 8 of 13; \"Origin: The Rapture\"","site_detail_url":"https:\/\/comicvine.gamespot.com\/artifacts-8-artifacts-part-8-of-13-origin-the-rapt\/4000-276826\/","issue_number":"8"},{"api_detail_url":"https:\/\/comicvine.gamespot.com\/api\/issue\/4000-285352\/","id":285352,"name":"\"Artifacts\" part 9 of 13; \"Origin: Wheel of Shadows\"","site_detail_url":"https:\/\/comicvine.gamespot.com\/artifacts-9-artifacts-part-9-of-13-origin-wheel-of\/4000-285352\/","issue_number":"9"},{"api_detail_url":"https:\/\/comicvine.gamespot.com\/api\/issue\/4000-293715\/","id":293715,"name":"\"Artifacts\" part 10 of 13; \"Origin: Glacier Stone\"","site_detail_url":"https:\/\/comicvine.gamespot.com\/artifacts-10-artifacts-part-10-of-13-origin-glacie\/4000-293715\/","issue_number":"10"},{"api_detail_url":"https:\/\/comicvine.gamespot.com\/api\/issue\/4000-301819\/","id":301819,"name":"\"Artifacts\" part 11 of 13; \"Origin: Pandora's Box\"","site_detail_url":"https:\/\/comicvine.gamespot.com\/artifacts-11-artifacts-part-11-of-13-origin-pandor\/4000-301819\/","issue_number":"11"},{"api_detail_url":"https:\/\/comicvine.gamespot.com\/api\/issue\/4000-308667\/","id":308667,"name":"\"Artifacts\" part 12 of 13; \"Origin: The Thirteenth\"","site_detail_url":"https:\/\/comicvine.gamespot.com\/artifacts-12-artifacts-part-12-of-13-origin-the-th\/4000-308667\/","issue_number":"12"},{"api_detail_url":"https:\/\/comicvine.gamespot.com\/api\/issue\/4000-309478\/","id":309478,"name":"\"Artifacts\" part 13 of 13; \"Origin: Heartstone\"","site_detail_url":"https:\/\/comicvine.gamespot.com\/artifacts-13-artifacts-part-13-of-13-origin-hearts\/4000-309478\/","issue_number":"13"},{"api_detail_url":"https:\/\/comicvine.gamespot.com\/api\/issue\/4000-315017\/","id":315017,"name":"New Creation, Part 1; Reborn","site_detail_url":"https:\/\/comicvine.gamespot.com\/artifacts-14-new-creation-part-1-reborn\/4000-315017\/","issue_number":"14"},{"api_detail_url":"https:\/\/comicvine.gamespot.com\/api\/issue\/4000-321555\/","id":321555,"name":"New Creation, Part 2","site_detail_url":"https:\/\/comicvine.gamespot.com\/artifacts-15-new-creation-part-2\/4000-321555\/","issue_number":"15"},{"api_detail_url":"https:\/\/comicvine.gamespot.com\/api\/issue\/4000-329698\/","id":329698,"name":"New Creation, Part 3","site_detail_url":"https:\/\/comicvine.gamespot.com\/artifacts-16-new-creation-part-3\/4000-329698\/","issue_number":"16"},{"api_detail_url":"https:\/\/comicvine.gamespot.com\/api\/issue\/4000-334991\/","id":334991,"name":"New Creation, Part 4","site_detail_url":"https:\/\/comicvine.gamespot.com\/artifacts-17-new-creation-part-4\/4000-334991\/","issue_number":"17"},{"api_detail_url":"https:\/\/comicvine.gamespot.com\/api\/issue\/4000-338574\/","id":338574,"name":"New Creation, Part 5","site_detail_url":"https:\/\/comicvine.gamespot.com\/artifacts-18-new-creation-part-5\/4000-338574\/","issue_number":"18"},{"api_detail_url":"https:\/\/comicvine.gamespot.com\/api\/issue\/4000-344171\/","id":344171,"name":"Phantoms of the Heart, Part 1","site_detail_url":"https:\/\/comicvine.gamespot.com\/artifacts-19-phantoms-of-the-heart-part-1\/4000-344171\/","issue_number":"19"},{"api_detail_url":"https:\/\/comicvine.gamespot.com\/api\/issue\/4000-349249\/","id":349249,"name":"Phantoms of the Heart, Part 2","site_detail_url":"https:\/\/comicvine.gamespot.com\/artifacts-20-phantoms-of-the-heart-part-2\/4000-349249\/","issue_number":"20"},{"api_detail_url":"https:\/\/comicvine.gamespot.com\/api\/issue\/4000-357645\/","id":357645,"name":"Phantoms of the Heart, Part 3","site_detail_url":"https:\/\/comicvine.gamespot.com\/artifacts-21-phantoms-of-the-heart-part-3\/4000-357645\/","issue_number":"21"},{"api_detail_url":"https:\/\/comicvine.gamespot.com\/api\/issue\/4000-363065\/","id":363065,"name":"Blood Rites, Part 1","site_detail_url":"https:\/\/comicvine.gamespot.com\/artifacts-22-blood-rites-part-1\/4000-363065\/","issue_number":"22"},{"api_detail_url":"https:\/\/comicvine.gamespot.com\/api\/issue\/4000-372341\/","id":372341,"name":"Blood Rites, Part 2","site_detail_url":"https:\/\/comicvine.gamespot.com\/artifacts-23-blood-rites-part-2\/4000-372341\/","issue_number":"23"},{"api_detail_url":"https:\/\/comicvine.gamespot.com\/api\/issue\/4000-378860\/","id":378860,"name":"Fallen From Heaven","site_detail_url":"https:\/\/comicvine.gamespot.com\/artifacts-24-fallen-from-heaven\/4000-378860\/","issue_number":"24"},{"api_detail_url":"https:\/\/comicvine.gamespot.com\/api\/issue\/4000-388529\/","id":388529,"name":"Progeny, Part 1","site_detail_url":"https:\/\/comicvine.gamespot.com\/artifacts-25-progeny-part-1\/4000-388529\/","issue_number":"25"},{"api_detail_url":"https:\/\/comicvine.gamespot.com\/api\/issue\/4000-394663\/","id":394663,"name":"Progeny, Part 4","site_detail_url":"https:\/\/comicvine.gamespot.com\/artifacts-26-progeny-part-4\/4000-394663\/","issue_number":"26"},{"api_detail_url":"https:\/\/comicvine.gamespot.com\/api\/issue\/4000-400126\/","id":400126,"name":"Truths & Destinies, Part 1","site_detail_url":"https:\/\/comicvine.gamespot.com\/artifacts-27-truths-destinies-part-1\/4000-400126\/","issue_number":"27"},{"api_detail_url":"https:\/\/comicvine.gamespot.com\/api\/issue\/4000-410330\/","id":410330,"name":"Truths & Destinies, Part 2","site_detail_url":"https:\/\/comicvine.gamespot.com\/artifacts-28-truths-destinies-part-2\/4000-410330\/","issue_number":"28"},{"api_detail_url":"https:\/\/comicvine.gamespot.com\/api\/issue\/4000-417943\/","id":417943,"name":"The Geometry of Hell","site_detail_url":"https:\/\/comicvine.gamespot.com\/artifacts-29-the-geometry-of-hell\/4000-417943\/","issue_number":"29"},{"api_detail_url":"https:\/\/comicvine.gamespot.com\/api\/issue\/4000-420618\/","id":420618,"name":"Wings","site_detail_url":"https:\/\/comicvine.gamespot.com\/artifacts-30-wings\/4000-420618\/","issue_number":"30"},{"api_detail_url":"https:\/\/comicvine.gamespot.com\/api\/issue\/4000-427029\/","id":427029,"name":"Light in the Darkness","site_detail_url":"https:\/\/comicvine.gamespot.com\/artifacts-31-light-in-the-darkness\/4000-427029\/","issue_number":"31"},{"api_detail_url":"https:\/\/comicvine.gamespot.com\/api\/issue\/4000-435102\/","id":435102,"name":"Hell, On Wheels","site_detail_url":"https:\/\/comicvine.gamespot.com\/artifacts-32-hell-on-wheels\/4000-435102\/","issue_number":"32"},{"api_detail_url":"https:\/\/comicvine.gamespot.com\/api\/issue\/4000-440269\/","id":440269,"name":"The Teacher and the Preacher","site_detail_url":"https:\/\/comicvine.gamespot.com\/artifacts-33-the-teacher-and-the-preacher\/4000-440269\/","issue_number":"33"},{"api_detail_url":"https:\/\/comicvine.gamespot.com\/api\/issue\/4000-444574\/","id":444574,"name":"A Man Amongst Gods","site_detail_url":"https:\/\/comicvine.gamespot.com\/artifacts-34-a-man-amongst-gods\/4000-444574\/","issue_number":"34"},{"api_detail_url":"https:\/\/comicvine.gamespot.com\/api\/issue\/4000-446520\/","id":446520,"name":"The Winter King: Finnegan's Wake","site_detail_url":"https:\/\/comicvine.gamespot.com\/artifacts-35-the-winter-king-finnegan-s-wake\/4000-446520\/","issue_number":"35"},{"api_detail_url":"https:\/\/comicvine.gamespot.com\/api\/issue\/4000-449620\/","id":449620,"name":"Killer Homework","site_detail_url":"https:\/\/comicvine.gamespot.com\/artifacts-36-killer-homework\/4000-449620\/","issue_number":"36"},{"api_detail_url":"https:\/\/comicvine.gamespot.com\/api\/issue\/4000-453448\/","id":453448,"name":"Teacher's Pet","site_detail_url":"https:\/\/comicvine.gamespot.com\/artifacts-37-teachers-pet\/4000-453448\/","issue_number":"37"},{"api_detail_url":"https:\/\/comicvine.gamespot.com\/api\/issue\/4000-462924\/","id":462924,"name":"Through a Glass, Darkly","site_detail_url":"https:\/\/comicvine.gamespot.com\/artifacts-38-through-a-glass-darkly\/4000-462924\/","issue_number":"38"},{"api_detail_url":"https:\/\/comicvine.gamespot.com\/api\/issue\/4000-465871\/","id":465871,"name":"The First Darkness","site_detail_url":"https:\/\/comicvine.gamespot.com\/artifacts-39-the-first-darkness\/4000-465871\/","issue_number":"39"},{"api_detail_url":"https:\/\/comicvine.gamespot.com\/api\/issue\/4000-469512\/","id":469512,"name":"Every Story \/ With Teeth \/ Fenrir's Curse \/ Blood and Dust","site_detail_url":"https:\/\/comicvine.gamespot.com\/artifacts-40-every-story-with-teeth-fenrirs-curse-\/4000-469512\/","issue_number":"40"}],"last_issue":{"api_detail_url":"https:\/\/comicvine.gamespot.com\/api\/issue\/4000-469512\/","id":469512,"name":"Every Story \/ With Teeth \/ Fenrir's Curse \/ Blood and Dust","issue_number":"40"},"locations":[{"api_detail_url":"https:\/\/comicvine.gamespot.com\/api\/location\/4020-56310\/","id":56310,"name":"New York State","site_detail_url":"https:\/\/comicvine.gamespot.com\/new-york-state\/4020-56310\/","count":"10"},{"api_detail_url":"https:\/\/comicvine.gamespot.com\/api\/location\/4020-41183\/","id":41183,"name":"New York City","site_detail_url":"https:\/\/comicvine.gamespot.com\/new-york-city\/4020-41183\/","count":"9"},{"api_detail_url":"https:\/\/comicvine.gamespot.com\/api\/location\/4020-55685\/","id":55685,"name":"Washington D.C.","site_detail_url":"https:\/\/comicvine.gamespot.com\/washington-dc\/4020-55685\/","count":"2"},{"api_detail_url":"https:\/\/comicvine.gamespot.com\/api\/location\/4020-55712\/","id":55712,"name":"New Jersey","site_detail_url":"https:\/\/comicvine.gamespot.com\/new-jersey\/4020-55712\/","count":"2"},{"api_detail_url":"https:\/\/comicvine.gamespot.com\/api\/location\/4020-55828\/","id":55828,"name":"Norway","site_detail_url":"https:\/\/comicvine.gamespot.com\/norway\/4020-55828\/","count":"2"},{"api_detail_url":"https:\/\/comicvine.gamespot.com\/api\/location\/4020-55907\/","id":55907,"name":"Ireland","site_detail_url":"https:\/\/comicvine.gamespot.com\/ireland\/4020-55907\/","count":"2"},{"api_detail_url":"https:\/\/comicvine.gamespot.com\/api\/location\/4020-57225\/","id":57225,"name":"Manhattan","site_detail_url":"https:\/\/comicvine.gamespot.com\/manhattan\/4020-57225\/","count":"2"},{"api_detail_url":"https:\/\/comicvine.gamespot.com\/api\/location\/4020-42471\/","id":42471,"name":"Hell","site_detail_url":"https:\/\/comicvine.gamespot.com\/hell\/4020-42471\/","count":"1"},{"api_detail_url":"https:\/\/comicvine.gamespot.com\/api\/location\/4020-55746\/","id":55746,"name":"Japan","site_detail_url":"https:\/\/comicvine.gamespot.com\/japan\/4020-55746\/","count":"1"},{"api_detail_url":"https:\/\/comicvine.gamespot.com\/api\/location\/4020-55778\/","id":55778,"name":"France","site_detail_url":"https:\/\/comicvine.gamespot.com\/france\/4020-55778\/","count":"1"},{"api_detail_url":"https:\/\/comicvine.gamespot.com\/api\/location\/4020-55820\/","id":55820,"name":"Mexico","site_detail_url":"https:\/\/comicvine.gamespot.com\/mexico\/4020-55820\/","count":"1"},{"api_detail_url":"https:\/\/comicvine.gamespot.com\/api\/location\/4020-55922\/","id":55922,"name":"Poland","site_detail_url":"https:\/\/comicvine.gamespot.com\/poland\/4020-55922\/","count":"1"},{"api_detail_url":"https:\/\/comicvine.gamespot.com\/api\/location\/4020-55952\/","id":55952,"name":"Saudi Arabia","site_detail_url":"https:\/\/comicvine.gamespot.com\/saudi-arabia\/4020-55952\/","count":"1"},{"api_detail_url":"https:\/\/comicvine.gamespot.com\/api\/location\/4020-56052\/","id":56052,"name":"Paris","site_detail_url":"https:\/\/comicvine.gamespot.com\/paris\/4020-56052\/","count":"1"},{"api_detail_url":"https:\/\/comicvine.gamespot.com\/api\/location\/4020-56944\/","id":56944,"name":"Africa","site_detail_url":"https:\/\/comicvine.gamespot.com\/africa\/4020-56944\/","count":"1"},{"api_detail_url":"https:\/\/comicvine.gamespot.com\/api\/location\/4020-57365\/","id":57365,"name":"Mexico City","site_detail_url":"https:\/\/comicvine.gamespot.com\/mexico-city\/4020-57365\/","count":"1"},{"api_detail_url":"https:\/\/comicvine.gamespot.com\/api\/location\/4020-57694\/","id":57694,"name":"Krakow","site_detail_url":"https:\/\/comicvine.gamespot.com\/krakow\/4020-57694\/","count":"1"},{"api_detail_url":"https:\/\/comicvine.gamespot.com\/api\/location\/4020-57894\/","id":57894,"name":"Mecca","site_detail_url":"https:\/\/comicvine.gamespot.com\/mecca\/4020-57894\/","count":"1"}],"name":"Artifacts","objects":[{"api_detail_url":"https:\/\/comicvine.gamespot.com\/api\/object\/4005-52130\/","id":52130,"name":"Tom Judge","site_detail_url":"https:\/\/comicvine.gamespot.com\/tom-judge\/4005-52130\/","count":"35"},{"api_detail_url":"https:\/\/comicvine.gamespot.com\/api\/object\/4005-52133\/","id":52133,"name":"Tilly Grimes","site_detail_url":"https:\/\/comicvine.gamespot.com\/tilly-grimes\/4005-52133\/","count":"25"},{"api_detail_url":"https:\/\/comicvine.gamespot.com\/api\/object\/4005-24347\/","id":24347,"name":"Jackie Estacado","site_detail_url":"https:\/\/comicvine.gamespot.com\/jackie-estacado\/4005-24347\/","count":"24"},{"api_detail_url":"https:\/\/comicvine.gamespot.com\/api\/object\/4005-43945\/","id":43945,"name":"The Angelus","site_detail_url":"https:\/\/comicvine.gamespot.com\/the-angelus\/4005-43945\/","count":"23"},{"api_detail_url":"https:\/\/comicvine.gamespot.com\/api\/object\/4005-48981\/","id":48981,"name":"Danielle Baptiste","site_detail_url":"https:\/\/comicvine.gamespot.com\/danielle-baptiste\/4005-48981\/","count":"22"},{"api_detail_url":"https:\/\/comicvine.gamespot.com\/api\/object\/4005-18318\/","id":18318,"name":"Sara Pezzini","site_detail_url":"https:\/\/comicvine.gamespot.com\/sara-pezzini\/4005-18318\/","count":"20"},{"api_detail_url":"https:\/\/comicvine.gamespot.com\/api\/object\/4005-43829\/","id":43829,"name":"Magdalena","site_detail_url":"https:\/\/comicvine.gamespot.com\/magdalena\/4005-43829\/","count":"19"},{"api_detail_url":"https:\/\/comicvine.gamespot.com\/api\/object\/4005-18319\/","id":18319,"name":"Witchblade","site_detail_url":"https:\/\/comicvine.gamespot.com\/witchblade\/4005-18319\/","count":"18"},{"api_detail_url":"https:\/\/comicvine.gamespot.com\/api\/object\/4005-48639\/","id":48639,"name":"Hope Pezzini","site_detail_url":"https:\/\/comicvine.gamespot.com\/hope-pezzini\/4005-48639\/","count":"16"},{"api_detail_url":"https:\/\/comicvine.gamespot.com\/api\/object\/4005-56215\/","id":56215,"name":"Aphrodite IV","site_detail_url":"https:\/\/comicvine.gamespot.com\/aphrodite-iv\/4005-56215\/","count":"16"},{"api_detail_url":"https:\/\/comicvine.gamespot.com\/api\/object\/4005-57559\/","id":57559,"name":"Glorianna Silver","site_detail_url":"https:\/\/comicvine.gamespot.com\/glorianna-silver\/4005-57559\/","count":"15"},{"api_detail_url":"https:\/\/comicvine.gamespot.com\/api\/object\/4005-56290\/","id":56290,"name":"Michael Finnegan","site_detail_url":"https:\/\/comicvine.gamespot.com\/michael-finnegan\/4005-56290\/","count":"14"},{"api_detail_url":"https:\/\/comicvine.gamespot.com\/api\/object\/4005-18323\/","id":18323,"name":"Ian Nottingham","site_detail_url":"https:\/\/comicvine.gamespot.com\/ian-nottingham\/4005-18323\/","count":"13"},{"api_detail_url":"https:\/\/comicvine.gamespot.com\/api\/object\/4005-60875\/","id":60875,"name":"Sabine","site_detail_url":"https:\/\/comicvine.gamespot.com\/sabine\/4005-60875\/","count":"12"},{"api_detail_url":"https:\/\/comicvine.gamespot.com\/api\/object\/4005-69653\/","id":69653,"name":"Alina Enstrom","site_detail_url":"https:\/\/comicvine.gamespot.com\/alina-enstrom\/4005-69653\/","count":"12"},{"api_detail_url":"https:\/\/comicvine.gamespot.com\/api\/object\/4005-76893\/","id":76893,"name":"Ji Xi","site_detail_url":"https:\/\/comicvine.gamespot.com\/ji-xi\/4005-76893\/","count":"11"},{"api_detail_url":"https:\/\/comicvine.gamespot.com\/api\/object\/4005-73479\/","id":73479,"name":"Mali","site_detail_url":"https:\/\/comicvine.gamespot.com\/mali\/4005-73479\/","count":"10"},{"api_detail_url":"https:\/\/comicvine.gamespot.com\/api\/object\/4005-15348\/","id":15348,"name":"Curator","site_detail_url":"https:\/\/comicvine.gamespot.com\/curator\/4005-15348\/","count":"9"},{"api_detail_url":"https:\/\/comicvine.gamespot.com\/api\/object\/4005-46761\/","id":46761,"name":"Necromancer","site_detail_url":"https:\/\/comicvine.gamespot.com\/necromancer\/4005-46761\/","count":"9"},{"api_detail_url":"https:\/\/comicvine.gamespot.com\/api\/object\/4005-57289\/","id":57289,"name":"Finch","site_detail_url":"https:\/\/comicvine.gamespot.com\/finch\/4005-57289\/","count":"8"},{"api_detail_url":"https:\/\/comicvine.gamespot.com\/api\/object\/4005-47571\/","id":47571,"name":"Jenny Romano","site_detail_url":"https:\/\/comicvine.gamespot.com\/jenny-romano\/4005-47571\/","count":"7"},{"api_detail_url":"https:\/\/comicvine.gamespot.com\/api\/object\/4005-82604\/","id":82604,"name":"Doctor Rachel Harrision","site_detail_url":"https:\/\/comicvine.gamespot.com\/doctor-rachel-harrision\/4005-82604\/","count":"6"},{"api_detail_url":"https:\/\/comicvine.gamespot.com\/api\/object\/4005-9151\/","id":9151,"name":"Velocity","site_detail_url":"https:\/\/comicvine.gamespot.com\/velocity\/4005-9151\/","count":"5"},{"api_detail_url":"https:\/\/comicvine.gamespot.com\/api\/object\/4005-24467\/","id":24467,"name":"Cyblade","site_detail_url":"https:\/\/comicvine.gamespot.com\/cyblade\/4005-24467\/","count":"5"},{"api_detail_url":"https:\/\/comicvine.gamespot.com\/api\/object\/4005-26501\/","id":26501,"name":"Ripclaw","site_detail_url":"https:\/\/comicvine.gamespot.com\/ripclaw\/4005-26501\/","count":"5"},{"api_detail_url":"https:\/\/comicvine.gamespot.com\/api\/object\/4005-40980\/","id":40980,"name":"Ellis","site_detail_url":"https:\/\/comicvine.gamespot.com\/ellis\/4005-40980\/","count":"5"},{"api_detail_url":"https:\/\/comicvine.gamespot.com\/api\/object\/4005-41824\/","id":41824,"name":"Ballistic","site_detail_url":"https:\/\/comicvine.gamespot.com\/ballistic\/4005-41824\/","count":"5"},{"api_detail_url":"https:\/\/comicvine.gamespot.com\/api\/object\/4005-43914\/","id":43914,"name":"Detective Gleason","site_detail_url":"https:\/\/comicvine.gamespot.com\/detective-gleason\/4005-43914\/","count":"4"},{"api_detail_url":"https:\/\/comicvine.gamespot.com\/api\/object\/4005-18327\/","id":18327,"name":"Julie Pezzini","site_detail_url":"https:\/\/comicvine.gamespot.com\/julie-pezzini\/4005-18327\/","count":"3"},{"api_detail_url":"https:\/\/comicvine.gamespot.com\/api\/object\/4005-40979\/","id":40979,"name":"Wolf","site_detail_url":"https:\/\/comicvine.gamespot.com\/wolf\/4005-40979\/","count":"3"},{"api_detail_url":"https:\/\/comicvine.gamespot.com\/api\/object\/4005-41080\/","id":41080,"name":"Samantha Argent","site_detail_url":"https:\/\/comicvine.gamespot.com\/samantha-argent\/4005-41080\/","count":"3"},{"api_detail_url":"https:\/\/comicvine.gamespot.com\/api\/object\/4005-41088\/","id":41088,"name":"Cloaker","site_detail_url":"https:\/\/comicvine.gamespot.com\/cloaker\/4005-41088\/","count":"2"},{"api_detail_url":"https:\/\/comicvine.gamespot.com\/api\/object\/4005-44424\/","id":44424,"name":"Heatwave","site_detail_url":"https:\/\/comicvine.gamespot.com\/heatwave\/4005-44424\/","count":"2"},{"api_detail_url":"https:\/\/comicvine.gamespot.com\/api\/object\/4005-58589\/","id":58589,"name":"Conductor","site_detail_url":"https:\/\/comicvine.gamespot.com\/conductor\/4005-58589\/","count":"2"},{"api_detail_url":"https:\/\/comicvine.gamespot.com\/api\/object\/4005-77679\/","id":77679,"name":"Interface","site_detail_url":"https:\/\/comicvine.gamespot.com\/interface\/4005-77679\/","count":"2"},{"api_detail_url":"https:\/\/comicvine.gamespot.com\/api\/object\/4005-85149\/","id":85149,"name":"Mike Long","site_detail_url":"https:\/\/comicvine.gamespot.com\/mike-long\/4005-85149\/","count":"2"},{"api_detail_url":"https:\/\/comicvine.gamespot.com\/api\/object\/4005-21923\/","id":21923,"name":"Stryker","site_detail_url":"https:\/\/comicvine.gamespot.com\/stryker\/4005-21923\/","count":"1"},{"api_detail_url":"https:\/\/comicvine.gamespot.com\/api\/object\/4005-43915\/","id":43915,"name":"Kenneth Irons","site_detail_url":"https:\/\/comicvine.gamespot.com\/kenneth-irons\/4005-43915\/","count":"1"},{"api_detail_url":"https:\/\/comicvine.gamespot.com\/api\/object\/4005-49791\/","id":49791,"name":"Azazel","site_detail_url":"https:\/\/comicvine.gamespot.com\/azazel\/4005-49791\/","count":"1"},{"api_detail_url":"https:\/\/comicvine.gamespot.com\/api\/object\/4005-52093\/","id":52093,"name":"Dr. Inder Chandrakhar","site_detail_url":"https:\/\/comicvine.gamespot.com\/dr-inder-chandrakhar\/4005-52093\/","count":"1"},{"api_detail_url":"https:\/\/comicvine.gamespot.com\/api\/object\/4005-61525\/","id":61525,"name":"Wulfgar","site_detail_url":"https:\/\/comicvine.gamespot.com\/wulfgar\/4005-61525\/","count":"1"},{"api_detail_url":"https:\/\/comicvine.gamespot.com\/api\/object\/4005-62333\/","id":62333,"name":"The Foreigner","site_detail_url":"https:\/\/comicvine.gamespot.com\/the-foreigner\/4005-62333\/","count":"1"},{"api_detail_url":"https:\/\/comicvine.gamespot.com\/api\/object\/4005-73816\/","id":73816,"name":"Locke","site_detail_url":"https:\/\/comicvine.gamespot.com\/locke\/4005-73816\/","count":"1"},{"api_detail_url":"https:\/\/comicvine.gamespot.com\/api\/object\/4005-85621\/","id":85621,"name":"Valko Balakov","site_detail_url":"https:\/\/comicvine.gamespot.com\/valko-balakov\/4005-85621\/","count":"1"},{"api_detail_url":"https:\/\/comicvine.gamespot.com\/api\/object\/4005-96079\/","id":96079,"name":"Matthew Strow","site_detail_url":"https:\/\/comicvine.gamespot.com\/matthew-strow\/4005-96079\/","count":"1"},{"api_detail_url":"https:\/\/comicvine.gamespot.com\/api\/object\/4005-103250\/","id":103250,"name":"Josephine Valmont","site_detail_url":"https:\/\/comicvine.gamespot.com\/josephine-valmont\/4005-103250\/","count":"1"},{"api_detail_url":"https:\/\/comicvine.gamespot.com\/api\/object\/4005-109292\/","id":109292,"name":"Salifah Zayid","site_detail_url":"https:\/\/comicvine.gamespot.com\/salifah-zayid\/4005-109292\/","count":"1"},{"api_detail_url":"https:\/\/comicvine.gamespot.com\/api\/object\/4005-117132\/","id":117132,"name":"Benedetta Maria Ferro","site_detail_url":"https:\/\/comicvine.gamespot.com\/benedetta-maria-ferro\/4005-117132\/","count":"1"}],"people":[{"api_detail_url":"https:\/\/comicvine.gamespot.com\/api\/person\/4040-42035\/","id":42035,"name":"Troy Peteri","site_detail_url":"https:\/\/comicvine.gamespot.com\/troy-peteri\/4040-42035\/","count":"40"},{"api_detail_url":"https:\/\/comicvine.gamespot.com\/api\/person\/4040-41799\/","id":41799,"name":"Ron Marz","site_detail_url":"https:\/\/comicvine.gamespot.com\/ron-marz\/4040-41799\/","count":"33"},{"api_detail_url":"https:\/\/comicvine.gamespot.com\/api\/person\/4040-44662\/","id":44662,"name":"Stjepan \u0160eji\u0107","site_detail_url":"https:\/\/comicvine.gamespot.com\/stjepan-sejic\/4040-44662\/","count":"27"},{"api_detail_url":"https:\/\/comicvine.gamespot.com\/api\/person\/4040-57996\/","id":57996,"name":"Bryan Rountree","site_detail_url":"https:\/\/comicvine.gamespot.com\/bryan-rountree\/4040-57996\/","count":"18"},{"api_detail_url":"https:\/\/comicvine.gamespot.com\/api\/person\/4040-48784\/","id":48784,"name":"Matt Hawkins","site_detail_url":"https:\/\/comicvine.gamespot.com\/matt-hawkins\/4040-48784\/","count":"17"},{"api_detail_url":"https:\/\/comicvine.gamespot.com\/api\/person\/4040-57997\/","id":57997,"name":"Filip Sablik","site_detail_url":"https:\/\/comicvine.gamespot.com\/filip-sablik\/4040-57997\/","count":"16"},{"api_detail_url":"https:\/\/comicvine.gamespot.com\/api\/person\/4040-59202\/","id":59202,"name":"John Tyler Christopher","site_detail_url":"https:\/\/comicvine.gamespot.com\/john-tyler-christopher\/4040-59202\/","count":"15"},{"api_detail_url":"https:\/\/comicvine.gamespot.com\/api\/person\/4040-68989\/","id":68989,"name":"Betsy Gonia","site_detail_url":"https:\/\/comicvine.gamespot.com\/betsy-gonia\/4040-68989\/","count":"15"},{"api_detail_url":"https:\/\/comicvine.gamespot.com\/api\/person\/4040-56887\/","id":56887,"name":"Sunny Gho","site_detail_url":"https:\/\/comicvine.gamespot.com\/sunny-gho\/4040-56887\/","count":"12"},{"api_detail_url":"https:\/\/comicvine.gamespot.com\/api\/person\/4040-15620\/","id":15620,"name":"Joe Weems","site_detail_url":"https:\/\/comicvine.gamespot.com\/joe-weems\/4040-15620\/","count":"8"},{"api_detail_url":"https:\/\/comicvine.gamespot.com\/api\/person\/4040-15688\/","id":15688,"name":"Marc Silvestri","site_detail_url":"https:\/\/comicvine.gamespot.com\/marc-silvestri\/4040-15688\/","count":"7"},{"api_detail_url":"https:\/\/comicvine.gamespot.com\/api\/person\/4040-42445\/","id":42445,"name":"Michael Broussard","site_detail_url":"https:\/\/comicvine.gamespot.com\/michael-broussard\/4040-42445\/","count":"7"},{"api_detail_url":"https:\/\/comicvine.gamespot.com\/api\/person\/4040-45557\/","id":45557,"name":"Philip W. Smith II","site_detail_url":"https:\/\/comicvine.gamespot.com\/philip-w-smith-ii\/4040-45557\/","count":"7"},{"api_detail_url":"https:\/\/comicvine.gamespot.com\/api\/person\/4040-73308\/","id":73308,"name":"Addison Duke","site_detail_url":"https:\/\/comicvine.gamespot.com\/addison-duke\/4040-73308\/","count":"7"},{"api_detail_url":"https:\/\/comicvine.gamespot.com\/api\/person\/4040-73094\/","id":73094,"name":"Ryan Cady","site_detail_url":"https:\/\/comicvine.gamespot.com\/ryan-cady\/4040-73094\/","count":"6"},{"api_detail_url":"https:\/\/comicvine.gamespot.com\/api\/person\/4040-1827\/","id":1827,"name":"Dale Keown","site_detail_url":"https:\/\/comicvine.gamespot.com\/dale-keown\/4040-1827\/","count":"5"},{"api_detail_url":"https:\/\/comicvine.gamespot.com\/api\/person\/4040-3380\/","id":3380,"name":"Todd McFarlane","site_detail_url":"https:\/\/comicvine.gamespot.com\/todd-mcfarlane\/4040-3380\/","count":"5"},{"api_detail_url":"https:\/\/comicvine.gamespot.com\/api\/person\/4040-4801\/","id":4801,"name":"Erik Larsen","site_detail_url":"https:\/\/comicvine.gamespot.com\/erik-larsen\/4040-4801\/","count":"5"},{"api_detail_url":"https:\/\/comicvine.gamespot.com\/api\/person\/4040-6024\/","id":6024,"name":"Whilce Portacio","site_detail_url":"https:\/\/comicvine.gamespot.com\/whilce-portacio\/4040-6024\/","count":"5"},{"api_detail_url":"https:\/\/comicvine.gamespot.com\/api\/person\/4040-18536\/","id":18536,"name":"Jim Valentino","site_detail_url":"https:\/\/comicvine.gamespot.com\/jim-valentino\/4040-18536\/","count":"5"},{"api_detail_url":"https:\/\/comicvine.gamespot.com\/api\/person\/4040-40977\/","id":40977,"name":"Robert Kirkman","site_detail_url":"https:\/\/comicvine.gamespot.com\/robert-kirkman\/4040-40977\/","count":"5"},{"api_detail_url":"https:\/\/comicvine.gamespot.com\/api\/person\/4040-42101\/","id":42101,"name":"Eric Stephenson","site_detail_url":"https:\/\/comicvine.gamespot.com\/eric-stephenson\/4040-42101\/","count":"5"},{"api_detail_url":"https:\/\/comicvine.gamespot.com\/api\/person\/4040-52492\/","id":52492,"name":"Jeremy Haun","site_detail_url":"https:\/\/comicvine.gamespot.com\/jeremy-haun\/4040-52492\/","count":"5"},{"api_detail_url":"https:\/\/comicvine.gamespot.com\/api\/person\/4040-62798\/","id":62798,"name":"Branwyn Bigglestone","site_detail_url":"https:\/\/comicvine.gamespot.com\/branwyn-bigglestone\/4040-62798\/","count":"5"},{"api_detail_url":"https:\/\/comicvine.gamespot.com\/api\/person\/4040-62799\/","id":62799,"name":"Drew Gill","site_detail_url":"https:\/\/comicvine.gamespot.com\/drew-gill\/4040-62799\/","count":"5"},{"api_detail_url":"https:\/\/comicvine.gamespot.com\/api\/person\/4040-66638\/","id":66638,"name":"Jennifer DeGuzman","site_detail_url":"https:\/\/comicvine.gamespot.com\/jennifer-deguzman\/4040-66638\/","count":"5"},{"api_detail_url":"https:\/\/comicvine.gamespot.com\/api\/person\/4040-72175\/","id":72175,"name":"Elena Salcedo","site_detail_url":"https:\/\/comicvine.gamespot.com\/elena-salcedo\/4040-72175\/","count":"5"},{"api_detail_url":"https:\/\/comicvine.gamespot.com\/api\/person\/4040-72176\/","id":72176,"name":"Jenna Savage","site_detail_url":"https:\/\/comicvine.gamespot.com\/jenna-savage\/4040-72176\/","count":"5"},{"api_detail_url":"https:\/\/comicvine.gamespot.com\/api\/person\/4040-72681\/","id":72681,"name":"Monica Garcia","site_detail_url":"https:\/\/comicvine.gamespot.com\/monica-garcia\/4040-72681\/","count":"5"},{"api_detail_url":"https:\/\/comicvine.gamespot.com\/api\/person\/4040-72682\/","id":72682,"name":"Tyler Shainline","site_detail_url":"https:\/\/comicvine.gamespot.com\/tyler-shainline\/4040-72682\/","count":"5"},{"api_detail_url":"https:\/\/comicvine.gamespot.com\/api\/person\/4040-72683\/","id":72683,"name":"Jonathan Chan","site_detail_url":"https:\/\/comicvine.gamespot.com\/jonathan-chan\/4040-72683\/","count":"5"},{"api_detail_url":"https:\/\/comicvine.gamespot.com\/api\/person\/4040-72686\/","id":72686,"name":"Emily Miller","site_detail_url":"https:\/\/comicvine.gamespot.com\/emily-miller\/4040-72686\/","count":"5"},{"api_detail_url":"https:\/\/comicvine.gamespot.com\/api\/person\/4040-72687\/","id":72687,"name":"Ron Richards","site_detail_url":"https:\/\/comicvine.gamespot.com\/ron-richards\/4040-72687\/","count":"5"},{"api_detail_url":"https:\/\/comicvine.gamespot.com\/api\/person\/4040-72804\/","id":72804,"name":"David Brothers","site_detail_url":"https:\/\/comicvine.gamespot.com\/david-brothers\/4040-72804\/","count":"5"},{"api_detail_url":"https:\/\/comicvine.gamespot.com\/api\/person\/4040-72807\/","id":72807,"name":"Emilio Bautista","site_detail_url":"https:\/\/comicvine.gamespot.com\/emilio-bautista\/4040-72807\/","count":"5"},{"api_detail_url":"https:\/\/comicvine.gamespot.com\/api\/person\/4040-73964\/","id":73964,"name":"Jeremy Sullivan","site_detail_url":"https:\/\/comicvine.gamespot.com\/jeremy-sullivan\/4040-73964\/","count":"5"},{"api_detail_url":"https:\/\/comicvine.gamespot.com\/api\/person\/4040-74560\/","id":74560,"name":"Meredith Wallace","site_detail_url":"https:\/\/comicvine.gamespot.com\/meredith-wallace\/4040-74560\/","count":"5"},{"api_detail_url":"https:\/\/comicvine.gamespot.com\/api\/person\/4040-74724\/","id":74724,"name":"Kat Salazar","site_detail_url":"https:\/\/comicvine.gamespot.com\/kat-salazar\/4040-74724\/","count":"5"},{"api_detail_url":"https:\/\/comicvine.gamespot.com\/api\/person\/4040-6025\/","id":6025,"name":"Sal Regla","site_detail_url":"https:\/\/comicvine.gamespot.com\/sal-regla\/4040-6025\/","count":"4"},{"api_detail_url":"https:\/\/comicvine.gamespot.com\/api\/person\/4040-55590\/","id":55590,"name":"Rick Basaldua","site_detail_url":"https:\/\/comicvine.gamespot.com\/rick-basaldua\/4040-55590\/","count":"4"},{"api_detail_url":"https:\/\/comicvine.gamespot.com\/api\/person\/4040-57552\/","id":57552,"name":"Marco Turini","site_detail_url":"https:\/\/comicvine.gamespot.com\/marco-turini\/4040-57552\/","count":"4"},{"api_detail_url":"https:\/\/comicvine.gamespot.com\/api\/person\/4040-61120\/","id":61120,"name":"William Farmer","site_detail_url":"https:\/\/comicvine.gamespot.com\/william-farmer\/4040-61120\/","count":"4"},{"api_detail_url":"https:\/\/comicvine.gamespot.com\/api\/person\/4040-75328\/","id":75328,"name":"-ROM-","site_detail_url":"https:\/\/comicvine.gamespot.com\/rom\/4040-75328\/","count":"4"},{"api_detail_url":"https:\/\/comicvine.gamespot.com\/api\/person\/4040-42847\/","id":42847,"name":"Kalman Andrasofszky","site_detail_url":"https:\/\/comicvine.gamespot.com\/kalman-andrasofszky\/4040-42847\/","count":"3"},{"api_detail_url":"https:\/\/comicvine.gamespot.com\/api\/person\/4040-48830\/","id":48830,"name":"Nelson Blake II","site_detail_url":"https:\/\/comicvine.gamespot.com\/nelson-blake-ii\/4040-48830\/","count":"3"},{"api_detail_url":"https:\/\/comicvine.gamespot.com\/api\/person\/4040-63302\/","id":63302,"name":"Eddy Swan","site_detail_url":"https:\/\/comicvine.gamespot.com\/eddy-swan\/4040-63302\/","count":"3"},{"api_detail_url":"https:\/\/comicvine.gamespot.com\/api\/person\/4040-76661\/","id":76661,"name":"Jessica Ambriz","site_detail_url":"https:\/\/comicvine.gamespot.com\/jessica-ambriz\/4040-76661\/","count":"3"},{"api_detail_url":"https:\/\/comicvine.gamespot.com\/api\/person\/4040-77224\/","id":77224,"name":"Tricia Ramos","site_detail_url":"https:\/\/comicvine.gamespot.com\/tricia-ramos\/4040-77224\/","count":"3"},{"api_detail_url":"https:\/\/comicvine.gamespot.com\/api\/person\/4040-4693\/","id":4693,"name":"Ryan Sook","site_detail_url":"https:\/\/comicvine.gamespot.com\/ryan-sook\/4040-4693\/","count":"2"},{"api_detail_url":"https:\/\/comicvine.gamespot.com\/api\/person\/4040-4798\/","id":4798,"name":"Andy Troy","site_detail_url":"https:\/\/comicvine.gamespot.com\/andy-troy\/4040-4798\/","count":"2"},{"api_detail_url":"https:\/\/comicvine.gamespot.com\/api\/person\/4040-42447\/","id":42447,"name":"Marco Galli","site_detail_url":"https:\/\/comicvine.gamespot.com\/marco-galli\/4040-42447\/","count":"2"},{"api_detail_url":"https:\/\/comicvine.gamespot.com\/api\/person\/4040-42807\/","id":42807,"name":"Arif Prianto","site_detail_url":"https:\/\/comicvine.gamespot.com\/arif-prianto\/4040-42807\/","count":"2"},{"api_detail_url":"https:\/\/comicvine.gamespot.com\/api\/person\/4040-53202\/","id":53202,"name":"Sheldon Mitchell","site_detail_url":"https:\/\/comicvine.gamespot.com\/sheldon-mitchell\/4040-53202\/","count":"2"},{"api_detail_url":"https:\/\/comicvine.gamespot.com\/api\/person\/4040-56372\/","id":56372,"name":"Dan Wickline","site_detail_url":"https:\/\/comicvine.gamespot.com\/dan-wickline\/4040-56372\/","count":"2"},{"api_detail_url":"https:\/\/comicvine.gamespot.com\/api\/person\/4040-56698\/","id":56698,"name":"Dulce Brassea","site_detail_url":"https:\/\/comicvine.gamespot.com\/dulce-brassea\/4040-56698\/","count":"2"},{"api_detail_url":"https:\/\/comicvine.gamespot.com\/api\/person\/4040-66889\/","id":66889,"name":"Jung-Geun Yoon","site_detail_url":"https:\/\/comicvine.gamespot.com\/jung-geun-yoon\/4040-66889\/","count":"2"},{"api_detail_url":"https:\/\/comicvine.gamespot.com\/api\/person\/4040-72685\/","id":72685,"name":"Jamie Parreno","site_detail_url":"https:\/\/comicvine.gamespot.com\/jamie-parreno\/4040-72685\/","count":"2"},{"api_detail_url":"https:\/\/comicvine.gamespot.com\/api\/person\/4040-73610\/","id":73610,"name":"Jaemie Dudas","site_detail_url":"https:\/\/comicvine.gamespot.com\/jaemie-dudas\/4040-73610\/","count":"2"},{"api_detail_url":"https:\/\/comicvine.gamespot.com\/api\/person\/4040-2052\/","id":2052,"name":"Tom Raney","site_detail_url":"https:\/\/comicvine.gamespot.com\/tom-raney\/4040-2052\/","count":"1"},{"api_detail_url":"https:\/\/comicvine.gamespot.com\/api\/person\/4040-2994\/","id":2994,"name":"Michael Avon Oeming","site_detail_url":"https:\/\/comicvine.gamespot.com\/michael-avon-oeming\/4040-2994\/","count":"1"},{"api_detail_url":"https:\/\/comicvine.gamespot.com\/api\/person\/4040-5477\/","id":5477,"name":"Phil Noto","site_detail_url":"https:\/\/comicvine.gamespot.com\/phil-noto\/4040-5477\/","count":"1"},{"api_detail_url":"https:\/\/comicvine.gamespot.com\/api\/person\/4040-5950\/","id":5950,"name":"Gina Going-Raney","site_detail_url":"https:\/\/comicvine.gamespot.com\/gina-going-raney\/4040-5950\/","count":"1"},{"api_detail_url":"https:\/\/comicvine.gamespot.com\/api\/person\/4040-6881\/","id":6881,"name":"Michael Golden","site_detail_url":"https:\/\/comicvine.gamespot.com\/michael-golden\/4040-6881\/","count":"1"},{"api_detail_url":"https:\/\/comicvine.gamespot.com\/api\/person\/4040-6964\/","id":6964,"name":"Tom Feister","site_detail_url":"https:\/\/comicvine.gamespot.com\/tom-feister\/4040-6964\/","count":"1"},{"api_detail_url":"https:\/\/comicvine.gamespot.com\/api\/person\/4040-7160\/","id":7160,"name":"Bart Sears","site_detail_url":"https:\/\/comicvine.gamespot.com\/bart-sears\/4040-7160\/","count":"1"},{"api_detail_url":"https:\/\/comicvine.gamespot.com\/api\/person\/4040-10046\/","id":10046,"name":"Greg Horn","site_detail_url":"https:\/\/comicvine.gamespot.com\/greg-horn\/4040-10046\/","count":"1"},{"api_detail_url":"https:\/\/comicvine.gamespot.com\/api\/person\/4040-13195\/","id":13195,"name":"Michael Atiyeh","site_detail_url":"https:\/\/comicvine.gamespot.com\/michael-atiyeh\/4040-13195\/","count":"1"},{"api_detail_url":"https:\/\/comicvine.gamespot.com\/api\/person\/4040-13762\/","id":13762,"name":"Steve Firchow","site_detail_url":"https:\/\/comicvine.gamespot.com\/steve-firchow\/4040-13762\/","count":"1"},{"api_detail_url":"https:\/\/comicvine.gamespot.com\/api\/person\/4040-13766\/","id":13766,"name":"Jason Gorder","site_detail_url":"https:\/\/comicvine.gamespot.com\/jason-gorder\/4040-13766\/","count":"1"},{"api_detail_url":"https:\/\/comicvine.gamespot.com\/api\/person\/4040-19216\/","id":19216,"name":"John Paul Leon","site_detail_url":"https:\/\/comicvine.gamespot.com\/john-paul-leon\/4040-19216\/","count":"1"},{"api_detail_url":"https:\/\/comicvine.gamespot.com\/api\/person\/4040-25609\/","id":25609,"name":"Ominous Studio","site_detail_url":"https:\/\/comicvine.gamespot.com\/ominous-studio\/4040-25609\/","count":"1"},{"api_detail_url":"https:\/\/comicvine.gamespot.com\/api\/person\/4040-28127\/","id":28127,"name":"Jim Mitchell","site_detail_url":"https:\/\/comicvine.gamespot.com\/jim-mitchell\/4040-28127\/","count":"1"},{"api_detail_url":"https:\/\/comicvine.gamespot.com\/api\/person\/4040-43084\/","id":43084,"name":"Mukesh Singh","site_detail_url":"https:\/\/comicvine.gamespot.com\/mukesh-singh\/4040-43084\/","count":"1"},{"api_detail_url":"https:\/\/comicvine.gamespot.com\/api\/person\/4040-43123\/","id":43123,"name":"Kenneth Rocafort","site_detail_url":"https:\/\/comicvine.gamespot.com\/kenneth-rocafort\/4040-43123\/","count":"1"},{"api_detail_url":"https:\/\/comicvine.gamespot.com\/api\/person\/4040-44601\/","id":44601,"name":"Nic Klein","site_detail_url":"https:\/\/comicvine.gamespot.com\/nic-klein\/4040-44601\/","count":"1"},{"api_detail_url":"https:\/\/comicvine.gamespot.com\/api\/person\/4040-46910\/","id":46910,"name":"Eric Canete","site_detail_url":"https:\/\/comicvine.gamespot.com\/eric-canete\/4040-46910\/","count":"1"},{"api_detail_url":"https:\/\/comicvine.gamespot.com\/api\/person\/4040-53071\/","id":53071,"name":"Facundo Percio","site_detail_url":"https:\/\/comicvine.gamespot.com\/facundo-percio\/4040-53071\/","count":"1"},{"api_detail_url":"https:\/\/comicvine.gamespot.com\/api\/person\/4040-53285\/","id":53285,"name":"Felix Serrano","site_detail_url":"https:\/\/comicvine.gamespot.com\/felix-serrano\/4040-53285\/","count":"1"},{"api_detail_url":"https:\/\/comicvine.gamespot.com\/api\/person\/4040-56316\/","id":56316,"name":"Paolo Pantalena","site_detail_url":"https:\/\/comicvine.gamespot.com\/paolo-pantalena\/4040-56316\/","count":"1"},{"api_detail_url":"https:\/\/comicvine.gamespot.com\/api\/person\/4040-61806\/","id":61806,"name":"Mike Odle","site_detail_url":"https:\/\/comicvine.gamespot.com\/mike-odle\/4040-61806\/","count":"1"},{"api_detail_url":"https:\/\/comicvine.gamespot.com\/api\/person\/4040-63184\/","id":63184,"name":"Jason Lewis","site_detail_url":"https:\/\/comicvine.gamespot.com\/jason-lewis\/4040-63184\/","count":"1"},{"api_detail_url":"https:\/\/comicvine.gamespot.com\/api\/person\/4040-68633\/","id":68633,"name":"Matthew Waite","site_detail_url":"https:\/\/comicvine.gamespot.com\/matthew-waite\/4040-68633\/","count":"1"},{"api_detail_url":"https:\/\/comicvine.gamespot.com\/api\/person\/4040-74725\/","id":74725,"name":"Chan-Hyuk Lee","site_detail_url":"https:\/\/comicvine.gamespot.com\/chan-hyuk-lee\/4040-74725\/","count":"1"},{"api_detail_url":"https:\/\/comicvine.gamespot.com\/api\/person\/4040-75329\/","id":75329,"name":"Kenny Porter","site_detail_url":"https:\/\/comicvine.gamespot.com\/kenny-porter\/4040-75329\/","count":"1"},{"api_detail_url":"https:\/\/comicvine.gamespot.com\/api\/person\/4040-75396\/","id":75396,"name":"Hannibal Tabu","site_detail_url":"https:\/\/comicvine.gamespot.com\/hannibal-tabu\/4040-75396\/","count":"1"},{"api_detail_url":"https:\/\/comicvine.gamespot.com\/api\/person\/4040-75534\/","id":75534,"name":"Martin Gimenez","site_detail_url":"https:\/\/comicvine.gamespot.com\/martin-gimenez\/4040-75534\/","count":"1"},{"api_detail_url":"https:\/\/comicvine.gamespot.com\/api\/person\/4040-75572\/","id":75572,"name":"Eugene Ward","site_detail_url":"https:\/\/comicvine.gamespot.com\/eugene-ward\/4040-75572\/","count":"1"},{"api_detail_url":"https:\/\/comicvine.gamespot.com\/api\/person\/4040-78538\/","id":78538,"name":"Vincent Valentine","site_detail_url":"https:\/\/comicvine.gamespot.com\/vincent-valentine\/4040-78538\/","count":"1"},{"api_detail_url":"https:\/\/comicvine.gamespot.com\/api\/person\/4040-80114\/","id":80114,"name":"Isaac Goodhart","site_detail_url":"https:\/\/comicvine.gamespot.com\/isaac-goodhart\/4040-80114\/","count":"1"},{"api_detail_url":"https:\/\/comicvine.gamespot.com\/api\/person\/4040-80389\/","id":80389,"name":"Devon Wong","site_detail_url":"https:\/\/comicvine.gamespot.com\/devon-wong\/4040-80389\/","count":"1"},{"api_detail_url":"https:\/\/comicvine.gamespot.com\/api\/person\/4040-80750\/","id":80750,"name":"Gustavo Brocanello","site_detail_url":"https:\/\/comicvine.gamespot.com\/gustavo-brocanello\/4040-80750\/","count":"1"},{"api_detail_url":"https:\/\/comicvine.gamespot.com\/api\/person\/4040-80751\/","id":80751,"name":"Raven Heisenberg","site_detail_url":"https:\/\/comicvine.gamespot.com\/raven-heisenberg\/4040-80751\/","count":"1"},{"api_detail_url":"https:\/\/comicvine.gamespot.com\/api\/person\/4040-81672\/","id":81672,"name":"Fabian Quintero","site_detail_url":"https:\/\/comicvine.gamespot.com\/fabian-quintero\/4040-81672\/","count":"1"},{"api_detail_url":"https:\/\/comicvine.gamespot.com\/api\/person\/4040-81673\/","id":81673,"name":"Adalor Alvarez","site_detail_url":"https:\/\/comicvine.gamespot.com\/adalor-alvarez\/4040-81673\/","count":"1"},{"api_detail_url":"https:\/\/comicvine.gamespot.com\/api\/person\/4040-81674\/","id":81674,"name":"Steve Foxe","site_detail_url":"https:\/\/comicvine.gamespot.com\/steve-foxe\/4040-81674\/","count":"1"}],"publisher":{"api_detail_url":"https:\/\/comicvine.gamespot.com\/api\/publisher\/4010-606\/","id":606,"name":"Top Cow"},"site_detail_url":"https:\/\/comicvine.gamespot.com\/artifacts\/4050-32864\/","start_year":"2010"},"version":"1.0"}